AUTHORS
MANIFEST.in
README.rst
setup.py
debian/.gitignore
debian/build-deb.sh
debian/changelog.in
debian/compat
debian/control
debian/copyright
debian/install
debian/neutron-opflex-agent.preinst
debian/neutron-opflex-agent.upstart
debian/rules
debian/source/format
etc/gbp-opflex.filters
etc/policy.json
neutron_opflex_agent.egg-info/PKG-INFO
neutron_opflex_agent.egg-info/SOURCES.txt
neutron_opflex_agent.egg-info/dependency_links.txt
neutron_opflex_agent.egg-info/entry_points.txt
neutron_opflex_agent.egg-info/pbr.json
neutron_opflex_agent.egg-info/top_level.txt
opflexagent/__init__.py
opflexagent/as_metadata_manager.py
opflexagent/constants.py
opflexagent/gbp_ovs_agent.py
opflexagent/opflex_notify.py
opflexagent/rpc.py
opflexagent/snat_iptables_manager.py
opflexagent/type_opflex.py
opflexagent/test/__init__.py
opflexagent/test/test_gbp_ovs_agent.py
rpm/build-rpm.sh
rpm/neutron-opflex-agent.service
rpm/neutron-opflex-agent.spec.in