Metadata-Version: 1.0
Name: neutron-opflex-agent
Version: 2014.2.0
Summary: This neutron agent provides edge policy enforcement.
Home-page: http://github.com/noironetworks/python-opflex-agent/
Author: Cisco Systems, Inc.
Author-email: apicapi@noironetworks.com
License: http://www.apache.org/licenses/LICENSE-2.0
Platform: UNKNOWN
